wscelery/__init__.py
wscelery/__main__.py
wscelery/app.py
wscelery/command.py
wscelery/events.py
wscelery/options.py
wscelery/urls.py
wscelery/utils.py
wscelery/websocket.py
wscelery/tests/__init__.py
wscelery/tests/test_command.py
wscelery/tests/test_utils.py
wscelery-0.2.0.dist-info/DESCRIPTION.rst
wscelery-0.2.0.dist-info/METADATA
wscelery-0.2.0.dist-info/RECORD
wscelery-0.2.0.dist-info/WHEEL
wscelery-0.2.0.dist-info/entry_points.txt
wscelery-0.2.0.dist-info/metadata.json
wscelery-0.2.0.dist-info/top_level.txt
