Metadata-Version: 2.0
Name: wscelery
Version: 0.2.0
Summary: Real time celery monitoring using websockets
Home-page: https://github.com/johan-sports/wscelery
Author: Antonis Kalou
Author-email: kalouantonis@gmail.com
License: MIT
Keywords: celery,websocket,monitoring
Platform: UNKNOWN
Classifier: Development Status :: 3 - Alpha
Classifier: Intended Audience :: Developers
Classifier: Topic :: System :: Distributed Computing
Classifier: License :: OSI Approved :: MIT License
Classifier: Programming Language :: Python
Classifier: Programming Language :: Python :: 3
Classifier: Programming Language :: Python :: 3.4
Classifier: Programming Language :: Python :: 3.5
Classifier: Programming Language :: Python :: 3.6
Classifier: Programming Language :: Python :: Implementation :: CPython
Classifier: Operating System :: OS Independent
Requires-Dist: cachetools (==2.0.0)
Requires-Dist: celery (>=4.0.2,<5.0)
Requires-Dist: tornado (==4.5)
